DIYables_MicroPython_DS18X20/DIYables_MicroPython_DS18X20.py
DIYables_MicroPython_DS18X20/__init__.py
DIYables_MicroPython_DS18X20-0.1.0.dist-info/LICENSE
DIYables_MicroPython_DS18X20-0.1.0.dist-info/METADATA
DIYables_MicroPython_DS18X20-0.1.0.dist-info/WHEEL
DIYables_MicroPython_DS18X20-0.1.0.dist-info/top_level.txt
DIYables_MicroPython_DS18X20-0.1.0.dist-info/RECORD
